maldives/__init__.py
maldives/env.py
maldives/api/__init__.py
maldives/api/fred.py
maldives/api/options.py
maldives/api/usda.py
maldives/backtest/__init__.py
maldives/backtest/utils.py
maldives/commodities/__init__.py
maldives/commodities/cattle.py
maldives/commodities/metals.py
maldives/maths/__init__.py
maldives/maths/numerical.py
maldives/maths/smoothing.py
maldives/options/__init__.py
maldives/options/implied_distribution.py
maldives/regression/__init__.py
maldives/regression/linear_model.py
maldives/timeseries/__init__.py
maldives/timeseries/timeseries.py
maldives/tuning/__init__.py
maldives/tuning/function.py
maldives/tuning/loss.py
maldives/utils/__init__.py
maldives/utils/array.py
maldives/utils/io.py
maldives/utils/plotting.py
maldives/utils/scrapping.py
maldives-0.0.32.dist-info/LICENSE
maldives-0.0.32.dist-info/METADATA
maldives-0.0.32.dist-info/WHEEL
maldives-0.0.32.dist-info/top_level.txt
maldives-0.0.32.dist-info/RECORD
